<?xml version="1.0" encoding="UTF-8"?><record_update table="question_choice">
    <question_choice action="INSERT_OR_UPDATE">
        <inactive>false</inactive>
        <order>200</order>
        <published_ref/>
        <question display_value="Priority">b495e2e887e41110496499383cbb354c</question>
        <sys_class_name>question_choice</sys_class_name>
        <sys_created_by>admin</sys_created_by>
        <sys_created_on>2022-07-04 13:46:58</sys_created_on>
        <sys_id>0bc5e2e887e41110496499383cbb350b</sys_id>
        <sys_mod_count>0</sys_mod_count>
        <sys_name>Normal</sys_name>
        <sys_package display_value="Treat management" source="x_824599_treat_man">dc022bae87c09110496499383cbb35d3</sys_package>
        <sys_policy/>
        <sys_scope display_value="Treat management">dc022bae87c09110496499383cbb35d3</sys_scope>
        <sys_update_name>question_choice_0bc5e2e887e41110496499383cbb350b</sys_update_name>
        <sys_updated_by>admin</sys_updated_by>
        <sys_updated_on>2022-07-04 13:46:58</sys_updated_on>
        <text>Normal</text>
        <value>normal</value>
    </question_choice>
    <fx_price action="delete_multiple" query="id=0bc5e2e887e41110496499383cbb350b"/>
</record_update>
